caretML/__init__.py
caretML/data.py
caretML/game_algorithms.py
caretML/graph_analysis.py
caretML/image_processing.py
caretML/machine_learning.py
caretML/numpy_operations.py
caretML/optimization_algorithms.py
caretML/tensor.py
caretML-0.1.0.dist-info/LICENSE
caretML-0.1.0.dist-info/METADATA
caretML-0.1.0.dist-info/WHEEL
caretML-0.1.0.dist-info/top_level.txt
caretML-0.1.0.dist-info/RECORD
