Metadata-Version: 2.1
Name: caretML
Version: 0.1.0
Summary: A utility library for machine learning inspired by lodash.
Author: David Condrey
Author-email: davidcondrey@protonmail.com
License: LICENSE
Classifier: Programming Language :: Python :: 3
Classifier: License :: OSI Approved :: MIT License
Classifier: Operating System :: OS Independent
License-File: LICENSE
Requires-Dist: numpy ==1.22.3
Requires-Dist: networkx ==2.6.3
Requires-Dist: python-louvain ==0.15
Requires-Dist: matplotlib ==3.5.1
Requires-Dist: plotly ==5.6.0
Requires-Dist: scipy ==1.7.3
Requires-Dist: scikit-learn ==1.0.2
Requires-Dist: scikit-image ==0.18.3
Requires-Dist: numba ==0.55.1
Requires-Dist: tensorflow ==2.8.0
Requires-Dist: pymoo ==0.5.0
